{
  "Description": "\"Adding marked.js to head and new styles for menu and markdown content\"",
  "Instruction": "\"Add marked.js CDN link and CSS styles for navigation menu and markdown content.\"",
  "ReplacementChunks": "[{\"AllowMultiple\":false,\"EndLine\":19,\"ReplacementContent\":\"  <!-- ECharts -->\\n  <script src=\\\"https://cdn.jsdelivr.net/npm/echarts/dist/echarts.min.js\\\"></script>\\n  <!-- Marked.js -->\\n  <script src=\\\"https://cdn.jsdelivr.net/npm/marked/marked.min.js\\\"></script>\",\"StartLine\":18,\"TargetContent\":\"  <!-- ECharts -->\\n  <script src=\\\"https://cdn.jsdelivr.net/npm/echarts/dist/echarts.min.js\\\"></script>\"},{\"AllowMultiple\":false,\"EndLine\":409,\"ReplacementContent\":\"    /* Responsive */\\n    @media (max-width: 1024px) {\\n      .charts-grid {\\n        grid-template-columns: 1fr;\\n      }\\n\\n      .chart-container {\\n        min-height: 300px;\\n      }\\n    }\\n\\n    /* Menu Bar */\\n    .menu-bar {\\n      display: flex;\\n      flex-wrap: wrap;\\n      gap: 1rem;\\n      border-bottom: 1px solid var(--border-subtle);\\n      padding-bottom: 1rem;\\n    }\\n\\n    .menu-btn {\\n      background: transparent;\\n      border: 1px solid var(--border-subtle);\\n      color: var(--text-secondary);\\n      font-size: 0.9rem;\\n      font-weight: 500;\\n      cursor: pointer;\\n      padding: 0.5rem 1rem;\\n      border-radius: 8px;\\n      transition: all 0.2s ease;\\n      font-family: inherit;\\n    }\\n\\n    .menu-btn:hover {\\n      background: rgba(255, 255, 255, 0.05);\\n      color: var(--text-primary);\\n    }\\n\\n    .menu-btn.active {\\n      background: var(--accent-primary);\\n      border-color: var(--accent-primary);\\n      color: #fff;\\n      box-shadow: 0 0 15px var(--accent-glow);\\n    }\\n\\n    /* Markdown Content */\\n    .md-content {\\n      background: var(--bg-surface);\\n      backdrop-filter: blur(12px);\\n      border: 1px solid var(--border-subtle);\\n      border-radius: 16px;\\n      padding: 2rem;\\n      color: var(--text-primary);\\n      line-height: 1.6;\\n    }\\n\\n    .md-content h1, .md-content h2, .md-content h3 {\\n      margin-top: 1.5rem;\\n      margin-bottom: 1rem;\\n      color: var(--text-primary);\\n    }\\n\\n    .md-content h1 { font-size: 1.8rem; border-bottom: 1px solid var(--border-subtle); padding-bottom: 0.5rem; margin\n<truncated 2913 bytes>",
  "TargetFile": "\"c:\\\\ANTIGRAVITY IDE FOLDER\\\\Dashboard Mitigasi Risiko Terintegrasi\\\\index.html\"",
  "toolAction": "\"Editing index.html\"",
  "toolSummary": "\"Edit index.html\""
}